dvsd_4bit_binary_counter.v
//************************************************************
// E BALAKRISHNA Verilog file: dvsd_4bit_binary_counter.v
// Verilog file: tb_dvsd_4bit_binary_counter.v
//************************************************************


// Declare input port and 4-bit output port to get the counter values  
  
 module dvsd_4bit_binary_counter (input clk,
                    input reset,
                    input updown,
                    output reg[3:0] out);

// This always block will be triggered at the rising edge of clk (0->1)  
// It checks if the reset is 0, then change out to zero   
// It checks if reset is 1, then the design should be allowed to count updown, so increment and decrement the counter   
  
  always @ (posedge clk) begin  
    if (reset)  
      out <= 0;
    else
        if(updown==1)
          if(out==15)
             out <= 0;  
           else
// Here, value increment by 1 for up counter

            out <= out + 1; 
        else          
           if(out==0)
              out<=15;
           else
// Here, value decrement by 1 for down counter

              out<= out-1;  
  end  
endmodule

tb_dvsd_4bit_binary_counter.v
//************************************************************
// E BALAKRISHNA 
// Verilog file: tb_dvsd_4bit_binary_counter.v
//************************************************************

`timescale 1ns / 1ps

// Declare a reg to connect to design clk
// Declare a reg to connect to design reset
// Declare a reg to connect to design updown 
// Declare a wire to connect to design output


module tb_dvsd_4bit_binary_counter; 
 reg clk; 
 reg reset;
 reg updown; 
 wire [3:0] out;
  
//Here a counter design and connect with Testbench variables  
  dvsd_4bit_binary_counter  c0 ( .clk (clk),  
          .reset (reset),
          .updown(updown),  
          .out (out));  
  
//Generate a clock with its value every 5ns -> time period = 10ns -> freq = 100 MHz  
   
 always #5 clk = ~clk;  
  
// This initial block forms the stimulus of the testbench  
  initial begin 
 
//Create a dump file 

  $dumpfile("tb_dvsd_4bit_binary_counter.vcd");                                        
  $dumpvars(0,tb_dvsd_4bit_binary_counter);
// Initialize testbench variables to 0 at start of simulation  
    clk <= 0;  
    reset <= 0;
    updown <= 0;  
  
// Drive rest of the stimulus, reset is asserted in between  
   #5     reset = 1;
         updown =0;
          
         updown =1;
          
   #30    reset = 0; 
         updown =0;
   #50   updown=1;
   #150   reset = 1;  
  
// Finish the stimulus after 200ns  
    #20 $finish;  
  end  
endmodule

tb_dvsd_4bit_binary_counter.vcd
$date
	Fri Aug 13 17:10:33 2021
$end
$version
	Icarus Verilog
$end
$timescale
	1ps
$end
$scope module tb_dvsd_4bit_binary_counter $end
$var wire 4 ! out [3:0] $end
$var reg 1 " clk $end
$var reg 1 # reset $end
$var reg 1 $ updown $end
$scope module c0 $end
$var wire 1 % clk $end
$var wire 1 & reset $end
$var wire 1 ' updown $end
$var reg 4 ( out [3:0] $end
$upscope $end
$upscope $end
$enddefinitions $end
#0
$dumpvars
bx (
0'
0&
0%
0$
0#
0"
bx !
$end
#5000
b0 (
b0 !
1$
1'
1#
1&
1"
1%
#10000
0"
0%
#15000
1"
1%
#20000
0"
0%
#25000
1"
1%
#30000
0"
0%
#35000
b1111 (
b1111 !
1"
1%
0$
0'
0#
0&
#40000
0"
0%
#45000
b1110 (
b1110 !
1"
1%
#50000
0"
0%
#55000
b1101 (
b1101 !
1"
1%
#60000
0"
0%
#65000
b1100 (
b1100 !
1"
1%
#70000
0"
0%
#75000
b1011 (
b1011 !
1"
1%
#80000
0"
0%
#85000
b1100 (
b1100 !
1"
1%
1$
1'
#90000
0"
0%
#95000
b1101 (
b1101 !
1"
1%
#100000
0"
0%
#105000
b1110 (
b1110 !
1"
1%
#110000
0"
0%
#115000
b1111 (
b1111 !
1"
1%
#120000
0"
0%
#125000
b0 (
b0 !
1"
1%
#130000
0"
0%
#135000
b1 (
b1 !
1"
1%
#140000
0"
0%
#145000
b10 (
b10 !
1"
1%
#150000
0"
0%
#155000
b11 (
b11 !
1"
1%
#160000
0"
0%
#165000
b100 (
b100 !
1"
1%
#170000
0"
0%
#175000
b101 (
b101 !
1"
1%
#180000
0"
0%
#185000
b110 (
b110 !
1"
1%
#190000
0"
0%
#195000
b111 (
b111 !
1"
1%
#200000
0"
0%
#205000
b1000 (
b1000 !
1"
1%
#210000
0"
0%
#215000
b1001 (
b1001 !
1"
1%
#220000
0"
0%
#225000
b1010 (
b1010 !
1"
1%
#230000
0"
0%
#235000
b0 (
b0 !
1"
1%
1#
1&
